app1/.DS_Store
app1/README.md
app1/__init__.py
app1/admin.py
app1/apps.py
app1/decorators.py
app1/forms.py
app1/models.py
app1/tests.py
app1/urls.py
app1/validate_api_key.py
app1/views.py
app1/__pycache__/__init__.cpython-311.pyc
app1/__pycache__/__init__.cpython-312.pyc
app1/__pycache__/admin.cpython-311.pyc
app1/__pycache__/admin.cpython-312.pyc
app1/__pycache__/apps.cpython-311.pyc
app1/__pycache__/apps.cpython-312.pyc
app1/__pycache__/cbfs.cpython-311.pyc
app1/__pycache__/chatbot.cpython-311.pyc
app1/__pycache__/config.cpython-311.pyc
app1/__pycache__/document_processing.cpython-311.pyc
app1/__pycache__/forms.cpython-311.pyc
app1/__pycache__/forms.cpython-312.pyc
app1/__pycache__/model_finetuning.cpython-311.pyc
app1/__pycache__/models.cpython-311.pyc
app1/__pycache__/models.cpython-312.pyc
app1/__pycache__/serializers.cpython-312.pyc
app1/__pycache__/urls.cpython-311.pyc
app1/__pycache__/urls.cpython-312.pyc
app1/__pycache__/views.cpython-311.pyc
app1/__pycache__/views.cpython-312.pyc
app1/migrations/.DS_Store
app1/migrations/0001_initial.py
app1/migrations/0002_conversation.py
app1/migrations/0003_conversation_session_key.py
app1/migrations/0004_rename_conversation_chatsession_and_more.py
app1/migrations/0005_remove_uploadedfile_name_uploadedfile_content.py
app1/migrations/0006_feedback.py
app1/migrations/0007_rename_bot_answer_feedback_answer_and_more.py
app1/migrations/0008_rename_user_id_chatsession_session_id.py
app1/migrations/0009_chatsession_start_time.py
app1/migrations/0010_remove_chatsession_session_id_alter_chatsession_id.py
app1/migrations/0011_rename_id_chatsession_session_id.py
app1/migrations/0012_alter_chatsession_session_id.py
app1/migrations/0013_chatsession_user_session_id.py
app1/migrations/0014_chatsession_user_id.py
app1/migrations/0015_remove_chatsession_created_at_and_more.py
app1/migrations/0016_chatsession_id.py
app1/migrations/0017_chatsession_question_asked_time_and_more.py
reliability_chatbot-0.34.dist-info/LICENSE
reliability_chatbot-0.34.dist-info/METADATA
reliability_chatbot-0.34.dist-info/WHEEL
reliability_chatbot-0.34.dist-info/entry_points.txt
reliability_chatbot-0.34.dist-info/top_level.txt
reliability_chatbot-0.34.dist-info/RECORD
